allkernAna/__init__.py
allkernAna/modulo.py
allkernAna-0.1.0.dist-info/METADATA
allkernAna-0.1.0.dist-info/WHEEL
allkernAna-0.1.0.dist-info/top_level.txt
allkernAna-0.1.0.dist-info/RECORD
